smartmask/__init__.py
smartmask/mask.py
smartmask-0.1.0.dist-info/METADATA
smartmask-0.1.0.dist-info/WHEEL
smartmask-0.1.0.dist-info/top_level.txt
smartmask-0.1.0.dist-info/RECORD
