Metadata-Version: 2.4
Name: smartmask
Version: 0.1.0
Summary: Simple smark masking of sensitive data
Author-email: sanjeev <sanjeevsanju929@gmail.com>
Requires-Python: >=3.7
